{
  "slug": "commodity-basic-description",
  "name": "Commodity basic description (type + species selection)",
  "url": "/notification/vnet/protected/notifications/DRAFT.GB.2026.1525979/consignment/page-4?commodity-selected-code=03019230&type=20",
  "pageTitle": "Select species of commodity",
  "caption": "Description of the goods",
  "heading": "Commodity",
  "bodyCopy": [],
  "backLink": "Back",
  "continueLabel": "Save and continue",
  "secondaryActions": [],
  "layout": "govuk-grid-row > govuk-grid-column-two-thirds",
  "structure": [
    {
      "element": "caption",
      "text": "Description of the goods",
      "govukComponent": "Caption (govuk-caption-xl)"
    },
    {
      "element": "h1",
      "text": "Commodity",
      "govukComponent": "Heading (govuk-heading-xl)"
    },
    {
      "element": "table",
      "text": "Commodity code | Description :: 03019230 | Of a length of 12cm or more but less than 20cm",
      "govukComponent": "Table"
    },
    {
      "element": "select",
      "text": "Type of commodity",
      "govukComponent": "Select"
    },
    {
      "element": "checkboxes",
      "text": "Select species of commodity / Select all that apply. / Anguilla anguilla / Anguilla spp.",
      "govukComponent": "Checkboxes"
    },
    {
      "element": "radios",
      "text": "Do you want to add another commodity? / Yes / No",
      "govukComponent": "Radios"
    },
    {
      "element": "button",
      "text": "Save and continue",
      "govukComponent": "Button"
    }
  ],
  "govukComponents": [
    {
      "component": "Caption",
      "govukClass": "govuk-caption-xl",
      "modifiers": [],
      "count": 1,
      "usage": "Section caption 'Description of the goods' above the H1",
      "evidence": "trace db2d277c5c8bfcf2dc0f2278bc92dc7aa8fdf42d action 22"
    },
    {
      "component": "Heading",
      "govukClass": "govuk-heading-xl",
      "modifiers": [],
      "count": 1,
      "usage": "Page H1 'Commodity'",
      "evidence": "trace db2d277c5c8bfcf2dc0f2278bc92dc7aa8fdf42d action 22"
    },
    {
      "component": "Table",
      "govukClass": "govuk-table",
      "modifiers": [
        "govuk-table__head",
        "govuk-table__header",
        "govuk-table__cell"
      ],
      "count": 1,
      "usage": "Read-only summary of the selected commodity code and its description (commodity code 03019230)",
      "evidence": "trace db2d277c5c8bfcf2dc0f2278bc92dc7aa8fdf42d action 22"
    },
    {
      "component": "Select",
      "govukClass": "govuk-select",
      "modifiers": [
        "govuk-!-width-one-half"
      ],
      "count": 1,
      "usage": "Type of commodity dropdown (Farmed stock / Wild stock)",
      "evidence": "trace db2d277c5c8bfcf2dc0f2278bc92dc7aa8fdf42d action 22"
    },
    {
      "component": "Checkboxes",
      "govukClass": "govuk-checkboxes",
      "modifiers": [
        "govuk-checkboxes__input",
        "govuk-checkboxes__item",
        "govuk-checkboxes__label"
      ],
      "count": 1,
      "usage": "Select species of commodity — multi-select species checkboxes (name=species)",
      "evidence": "trace db2d277c5c8bfcf2dc0f2278bc92dc7aa8fdf42d action 22"
    },
    {
      "component": "Radios",
      "govukClass": "govuk-radios",
      "modifiers": [
        "govuk-radios__input",
        "govuk-radios__item",
        "govuk-radios__label",
        "govuk-!-width-one-half"
      ],
      "count": 1,
      "usage": "Do you want to add another commodity? Yes/No (name=addCommodity); radios group carries govuk-!-width-one-half",
      "evidence": "trace db2d277c5c8bfcf2dc0f2278bc92dc7aa8fdf42d action 22"
    },
    {
      "component": "Fieldset",
      "govukClass": "govuk-fieldset",
      "modifiers": [
        "govuk-fieldset__legend",
        "govuk-fieldset__legend--m",
        "govuk-label--m"
      ],
      "count": 2,
      "usage": "Wraps the species checkboxes group and the add-another-commodity radios group. Species legend uses the standard govuk-fieldset__legend--m; the add-another-commodity legend instead mixes govuk-fieldset__legend with govuk-label--m (a non-standard legend-sizing class rather than govuk-fieldset__legend--m)",
      "evidence": "trace db2d277c5c8bfcf2dc0f2278bc92dc7aa8fdf42d action 22 — species legend class 'govuk-fieldset__legend govuk-fieldset__legend--m'; addCommodity legend class 'govuk-fieldset__legend govuk-label--m'"
    },
    {
      "component": "Hint",
      "govukClass": "govuk-hint",
      "modifiers": [],
      "count": 1,
      "usage": "'Select all that apply.' hint for the species checkboxes (id=species-hint)",
      "evidence": "trace db2d277c5c8bfcf2dc0f2278bc92dc7aa8fdf42d action 22"
    },
    {
      "component": "Label",
      "govukClass": "govuk-label",
      "modifiers": [
        "govuk-label--m",
        "govuk-label--s",
        ""
      ],
      "count": 5,
      "usage": "Label for the Type of commodity select (govuk-label--m, 1); the two species checkbox item labels (govuk-checkboxes__label govuk-label--s, 2); the two add-another-commodity radio labels (govuk-radios__label, plain govuk-label with no size modifier, 2)",
      "evidence": "trace db2d277c5c8bfcf2dc0f2278bc92dc7aa8fdf42d action 22 — 5 elements with class govuk-label: type-select label (--m), 'Anguilla anguilla'/'Anguilla spp.' checkbox labels (--s), 'Yes'/'No' radio labels (plain)"
    },
    {
      "component": "Button",
      "govukClass": "govuk-button",
      "modifiers": [
        "govuk-!-margin-right-1",
        "govuk-!-margin-bottom-4"
      ],
      "count": 1,
      "usage": "Primary 'Save and continue' submit button",
      "evidence": "trace db2d277c5c8bfcf2dc0f2278bc92dc7aa8fdf42d action 22"
    },
    {
      "component": "Form group",
      "govukClass": "govuk-form-group",
      "modifiers": [],
      "count": 3,
      "usage": "Standard form-group wrappers: one around the Type-of-commodity select, one around the species checkboxes fieldset, one around the add-another-commodity radios fieldset",
      "evidence": "trace db2d277c5c8bfcf2dc0f2278bc92dc7aa8fdf42d action 22 — three govuk-form-group divs in the DOM"
    }
  ],
  "nonStandardPatterns": [
    {
      "pattern": "table-responsive",
      "whatItDoes": "Custom wrapper class around the govuk-table for horizontal-scroll / responsive behaviour on narrow viewports",
      "concern": "Not part of the GOV.UK Design System — bespoke responsive-table shim. The commodity summary is a fixed 2-column table (code + description) that fits comfortably; a plain govuk-table needs no custom wrapper.",
      "govukAlternative": "Standard GOV.UK Table (govuk-table) with no wrapper; if wide-table scrolling is genuinely needed, wrap in a simple overflow-x container rather than a bespoke class.",
      "evidence": "trace db2d277c5c8bfcf2dc0f2278bc92dc7aa8fdf42d action 22"
    },
    {
      "pattern": "commodity-type",
      "whatItDoes": "IPAFFS-specific class applied to the Type-of-commodity <select> (alongside govuk-select and govuk-!-width-one-half)",
      "concern": "Bespoke hook class on an otherwise-standard govuk-select. Likely a CSS/JS selector hook rather than a distinct component; carries no design intent beyond the standard govuk-!-width-one-half modifier already present.",
      "govukAlternative": "Standard GOV.UK Select with width utility only; drop the bespoke class or replace with data-* hook if JS binding is required.",
      "evidence": "trace db2d277c5c8bfcf2dc0f2278bc92dc7aa8fdf42d action 22"
    }
  ],
  "fields": [
    {
      "name": "type",
      "label": "Type of commodity",
      "control": "select",
      "required": false,
      "options": [
        "Farmed stock",
        "Wild stock"
      ],
      "optionsTruncated": false,
      "optionCount": 2,
      "observedValues": [
        "Farmed stock"
      ],
      "conditionalOn": "The Type-of-commodity control is itself conditionally present — it renders only for commodity codes that carry a type taxonomy. Tests drive a non-taxonomy commodity (code 96020000) with typeOfCommodity='' (ched-p-auto-clearance.spec.ts:56) and the workflow only selects a type when one is configured (`if (typeOfCommodity)` — ched-p-workflows.ts:293), confirming some codes render no type dropdown at all. The OPTION SET is also commodity-code-specific reference data: for the IUU/fish code 03019230 the trace rendered Farmed stock (value 20) / Wild stock (value 61); the domain vocabulary the tests use enumerates FOUR labels across all CHED-P commodities — Domestic, Farmed game, Farmed stock, Wild game (types/commodity-type.ts) — of which meat codes select Farmed game (DEFAULT_CONFIG, ched-p-workflows.ts:127) and domestic lamb selects Domestic (ched-p-workflows.ts:686). Only Farmed stock / Wild stock apply to the fish/IUU codes. The new app should source this list from a reference-data service keyed on commodity code, not hardcode it.",
      "confidence": "confirmed",
      "evidence": "trace db2d277c5c8bfcf2dc0f2278bc92dc7aa8fdf42d action 22 — <select id=type-select name=type>, option values 20=Farmed stock (selected) / 61=Wild stock. IUU/fish flow selects 'Farmed stock' by label via dropdownTypeOfCommodity.selectOption({label: commodityType.farmedStock}) — ched-p-workflows.ts:871; commodityType.farmedStock = 'Farmed stock' — types/commodity-type.ts:4. The trace's commodity-selected-code=03019230 is exactly commodityCode.carpFish (types/commodity-code.ts:5), which the fish workflow fills at ched-p-workflows.ts:866, binding this trace to the createChedPFishNotification path. Page object dropdownTypeOfCommodity = getByLabel('Type of commodity') — CommodityBasicDescriptionPage.ts:6-8"
    },
    {
      "name": "species",
      "label": "Select species of commodity",
      "hint": "Select all that apply.",
      "control": "checkbox",
      "required": false,
      "options": [
        "Anguilla anguilla",
        "Anguilla spp."
      ],
      "optionsTruncated": false,
      "optionCount": 2,
      "observedValues": [
        "Anguilla spp."
      ],
      "conditionalOn": "Species list is driven by the selected commodity code (03019230 in this trace, an eel/Anguilla commodity); other commodity codes present a different species list, and non-taxonomy codes present NONE — tests drive code 96020000 with species='' (ched-p-auto-clearance.spec.ts:57) and the workflow only checks a species box when one is configured (`if (species)` — ched-p-workflows.ts:296). It is a multi-select (checkboxes, 'Select all that apply.') though the fish workflow only ticks a single species. Other fish species the tests exercise for different codes: Acetes spp., Acipenser spp. (types/species.ts). Reference data — the new app should source species from a reference-data service keyed on commodity code, not hardcode this list.",
      "confidence": "confirmed",
      "evidence": "trace db2d277c5c8bfcf2dc0f2278bc92dc7aa8fdf42d action 22 — checkbox name=species, value=1756325 id='Anguilla spp.-checkbox'; sibling 'Anguilla anguilla-checkbox'. IUU/fish flow waits for + checks 'Anguilla spp.' by exact accessible name — ched-p-workflows.ts:872-873; species.anguillaSpp = 'Anguilla spp.' — types/species.ts:10. Confirmed multi-select via checkboxSpecies(name).check(): the generic flow ticks whatever single species is configured (ched-p-workflows.ts:296-298), never more than one, so the multi-tick path is un-exercised. Page object checkboxSpecies(name) = getByRole('checkbox', {name, exact:true}) — CommodityBasicDescriptionPage.ts:10-12"
    },
    {
      "name": "addCommodity",
      "label": "Do you want to add another commodity?",
      "control": "radio",
      "required": false,
      "options": [
        "Yes",
        "No"
      ],
      "optionsTruncated": false,
      "optionCount": 2,
      "observedValues": [
        "No"
      ],
      "conditionalOn": "The 'Yes' branch opens an add-another-commodity loop (multiple commodities per notification). The IUU/fish workflow always selects 'No' (single commodity) — ched-p-workflows.ts:874 — so the 'Yes'/multi-commodity path is a real but un-exercised branch in this corpus. The page object only exposes radioNo (CommodityBasicDescriptionPage.ts:18-20), consistent with tests never taking the 'Yes' path.",
      "confidence": "confirmed",
      "evidence": "trace db2d277c5c8bfcf2dc0f2278bc92dc7aa8fdf42d action 22 — radios name=addCommodity, ids addCommodity / addCommodity-2. Workflow selects 'No' via getByRole('radio',{name:'No'}) — ched-p-workflows.ts:874, CommodityBasicDescriptionPage.ts:18-20"
    }
  ],
  "validationMessages": [],
  "confidence": "confirmed",
  "openQuestions": [
    "VALIDATION COPY IS A GAP. The `required` attribute is false on all three controls in the DOM, but validation is almost certainly server-side (this trace is a happy path with no error state). No CHED-P test asserts any validation/error-message string for this page (grep of tests/notification/ched-p/* and tests/accessibility/* found only happy-path field fills, no expect() on error copy), so we have NEITHER trace nor test evidence for error messages. The species selection and add-another-commodity radio are likely mandatory when their controls render — but their exact error copy needs a trace with a validation error to confirm. Left as an honest gap for a human.",
    "The species checkbox list is commodity-code-specific reference data (here Anguilla anguilla / Anguilla spp. for code 03019230). Both the species list AND the Type-of-commodity option list are keyed on commodity code, and both controls are ENTIRELY ABSENT for non-taxonomy codes (tests pass typeOfCommodity='' and species='' for code 96020000 — ched-p-auto-clearance.spec.ts:56-57). Confirm the full species taxonomy and the type option-set against the reference-data service; not derivable from traces alone (traces are a lower bound — only Anguilla-code species were exercised).",
    "The 'Type of commodity' select for fish codes offers Farmed stock (20) / Wild stock (61). The wider CHED-P domain vocabulary the tests use has four labels — Domestic, Farmed game, Farmed stock, Wild game (types/commodity-type.ts) — which apply to meat/other codes, NOT fish. Confirm the fish/IUU code set only ever offers Farmed stock / Wild stock, and how 'Farmed' vs 'Wild' feeds downstream (IUU catch-certificate applicability likely turns on wild-caught).",
    "The shared page object (CommodityBasicDescriptionPage.ts) exposes a CHED-PP (plants) variant of this page — an EPPO-code textbox + Search + 'Add ' button + a #{species}-checkbox locator (lines 14,22-32). These are NOT used by the IUU/fish flow (which renders species as a fixed checkbox list). Excluded from this IUU page's fields because it is CHED-PP-only and was not rendered in the IUU trace. Confirm the IUU journey never needs EPPO-code species search.",
    "A hidden input name=class (id=class-select-hidden) and hidden ids type-id/class-id/family-id/complement-id carry the taxonomy identifiers — the visible select only exposes 'type'; the class/family layer of the IPAFFS commodity taxonomy is not surfaced on this page in this trace. The separate CommodityClassPage page object (a 'Select class' dropdown) suggests class can be its own page for some commodities — confirm whether IUU/fish codes ever route through a class-selection step.",
    "IPAFFS ARCHITECTURE the new app should NOT copy: this single page contains TWO separate <form>s. The Type-of-commodity <select> sits in its own GET form (id=categories, action=page-4) with a hidden name=class; the species checkboxes + add-another-commodity radios + Save-and-continue button sit in a SECOND POST form (action=page-4). Changing the type therefore triggers a GET page reload (page-4?commodity-selected-code=…&type=…) that re-renders the species checkbox list for the newly-selected type. This is a legacy round-trip/repopulation pattern; the new CDP app should populate species reactively from a reference-data service keyed on (commodity code, type) without a full-page GET reload. Confirmed: DOM at action 22 shows both forms; the network shows GET page-4?commodity-selected-code=03019230 (request 3791) followed by a GET with &type appended (request 3808)."
  ]
}
